.gitignore
.mailmap
.prospector.yaml
.readthedocs.yml
.zenodo.json
CODEOWNERS
LICENSE
MANIFEST.in
README.rst
environment.yml
setup.py
.github/install.sh
.github/release-drafter.yml
.github/workflows/ci.yml
.github/workflows/release-drafter.yml
docs/AUTHORS.rst
docs/CHANGELOG.rst
docs/Makefile
docs/conf.py
docs/index.rst
docs/make.bat
docs/contribute/beforepushing.rst
docs/contribute/gitrepo.rst
docs/contribute/index.rst
docs/contribute/instructions.rst
docs/contribute/benchmarks/DL2/benchmarks_DL2_direction-reconstruction.ipynb
docs/contribute/benchmarks/DL2/benchmarks_DL2_particle-classification.ipynb
docs/contribute/benchmarks/DL3/benchmarks_DL3_IRFs_and_sensitivity.ipynb
docs/contribute/benchmarks/DL3/benchmarks_DL3_cuts_optimization.ipynb
docs/contribute/benchmarks/DL3/overall_performance_plot_CTA.ipynb
docs/contribute/benchmarks/DL3/requirements/North-05h-LST.dat
docs/contribute/benchmarks/DL3/requirements/North-05h-MST.dat
docs/contribute/benchmarks/DL3/requirements/North-05h.dat
docs/contribute/benchmarks/DL3/requirements/North-30m-EffectiveArea.dat
docs/contribute/benchmarks/DL3/requirements/North-30m-LST-EffectiveArea.dat
docs/contribute/benchmarks/DL3/requirements/North-30m-LST.dat
docs/contribute/benchmarks/DL3/requirements/North-30m-MST-EffectiveArea.dat
docs/contribute/benchmarks/DL3/requirements/North-30m-MST.dat
docs/contribute/benchmarks/DL3/requirements/North-30m.dat
docs/contribute/benchmarks/DL3/requirements/North-50h-AngRes.dat
docs/contribute/benchmarks/DL3/requirements/North-50h-ERes.dat
docs/contribute/benchmarks/DL3/requirements/North-50h-LST-AngRes.dat
docs/contribute/benchmarks/DL3/requirements/North-50h-LST-ERes.dat
docs/contribute/benchmarks/DL3/requirements/North-50h-LST.dat
docs/contribute/benchmarks/DL3/requirements/North-50h-MST-AngRes.dat
docs/contribute/benchmarks/DL3/requirements/North-50h-MST-ERes.dat
docs/contribute/benchmarks/DL3/requirements/North-50h-MST.dat
docs/contribute/benchmarks/DL3/requirements/North-50h.dat
protopipe.egg-info/PKG-INFO
protopipe.egg-info/SOURCES.txt
protopipe.egg-info/dependency_links.txt
protopipe.egg-info/not-zip-safe
protopipe.egg-info/requires.txt
protopipe.egg-info/top_level.txt
