Metadata-Version: 2.1
Name: protopipe
Version: 0.4.0.post1
Summary: Prototype pipeline for the Cherenkov Telescope Array (CTA)
Home-page: https://github.com/cta-observatory/protopipe
Author: Michele Peresano
Author-email: michele.peresano@cea.fr
License: MIT
Platform: UNKNOWN
Provides-Extra: all
Provides-Extra: tests
Provides-Extra: docs
